number_parser/VERSION
number_parser/__init__.py
number_parser/parser.py
number_parser/data/__init__.py
number_parser/data/af.py
number_parser/data/ak.py
number_parser/data/am.py
number_parser/data/ar.py
number_parser/data/az.py
number_parser/data/be.py
number_parser/data/bg.py
number_parser/data/bs.py
number_parser/data/ca.py
number_parser/data/ccp.py
number_parser/data/chr.py
number_parser/data/cs.py
number_parser/data/cy.py
number_parser/data/da.py
number_parser/data/de-CH.py
number_parser/data/de.py
number_parser/data/ee.py
number_parser/data/el.py
number_parser/data/en-IN.py
number_parser/data/en.py
number_parser/data/eo.py
number_parser/data/es.py
number_parser/data/et.py
number_parser/data/fa-AF.py
number_parser/data/fa.py
number_parser/data/ff.py
number_parser/data/fi.py
number_parser/data/fil.py
number_parser/data/fo.py
number_parser/data/fr-BE.py
number_parser/data/fr-CH.py
number_parser/data/fr.py
number_parser/data/ga.py
number_parser/data/he.py
number_parser/data/hi.py
number_parser/data/hr.py
number_parser/data/hu.py
number_parser/data/hy.py
number_parser/data/id.py
number_parser/data/is.py
number_parser/data/it.py
number_parser/data/ja.py
number_parser/data/ka.py
number_parser/data/kl.py
number_parser/data/km.py
number_parser/data/ko.py
number_parser/data/ky.py
number_parser/data/lb.py
number_parser/data/lo.py
number_parser/data/lrc.py
number_parser/data/lt.py
number_parser/data/lv.py
number_parser/data/mk.py
number_parser/data/ms.py
number_parser/data/mt.py
number_parser/data/my.py
number_parser/data/nb.py
number_parser/data/nl.py
number_parser/data/nn.py
number_parser/data/pl.py
number_parser/data/pt-PT.py
number_parser/data/pt.py
number_parser/data/qu.py
number_parser/data/ro.py
number_parser/data/root.py
number_parser/data/ru.py
number_parser/data/se.py
number_parser/data/sk.py
number_parser/data/sl.py
number_parser/data/sq.py
number_parser/data/sr-Latn.py
number_parser/data/sr.py
number_parser/data/su.py
number_parser/data/sv.py
number_parser-0.3.2.dist-info/LICENSE
number_parser-0.3.2.dist-info/METADATA
number_parser-0.3.2.dist-info/WHEEL
number_parser-0.3.2.dist-info/top_level.txt
number_parser-0.3.2.dist-info/RECORD
